aioheroku3/__init__.py
aioheroku3/core.py
aioheroku3/errors/__init__.py
aioheroku3/errors/unauthorized_401.py
aioheroku3/methods/__init__.py
aioheroku3/methods/accounts/__init__.py
aioheroku3/methods/accounts/get_account_info.py
aioheroku3/methods/accounts/login.py
aioheroku3-2.0.dist-info/LICENSE
aioheroku3-2.0.dist-info/METADATA
aioheroku3-2.0.dist-info/WHEEL
aioheroku3-2.0.dist-info/top_level.txt
aioheroku3-2.0.dist-info/RECORD
