Metadata-Version: 2.1
Name: aioheroku3
Version: 2.0
Summary: Asynchronous Heroku wrapper library.
Home-page: https://github.com/DoellBarr/aioheroku3
Author: ShohihAbdul
Author-email: shohih242@gmail.com
License: MIT
Classifier: Development Status :: 5 - Production/Stable
Classifier: Intended Audience :: Developers
Classifier: Natural Language :: English
Classifier: License :: OSI Approved :: MIT License
Classifier: Programming Language :: Python
Classifier: Programming Language :: Python :: 3.7
Classifier: Programming Language :: Python :: 3.8
Classifier: Programming Language :: Python :: 3.9
Classifier: Programming Language :: Python :: 3.10
License-File: LICENSE
